vatcalc/__init__.py
vatcalc/py.typed
vatcalc/simple.py
vatcalc-1.0.0.dist-info/METADATA
vatcalc-1.0.0.dist-info/WHEEL
vatcalc-1.0.0.dist-info/licenses/LICENSE
vatcalc-1.0.0.dist-info/RECORD
