Metadata-Version: 2.3
Name: vatcalc
Version: 1.0.0
Summary: A simple VAT based price calculator
Author-email: Sasha Matijasic <sasha@selectnull.com>
Classifier: Development Status :: 5 - Production/Stable
Classifier: License :: OSI Approved :: MIT License
Classifier: Programming Language :: Python :: 3.9
Classifier: Topic :: Office/Business :: Financial
Requires-Python: >=3.9
